{
    "overall_acc": 0.7903361344537815,
    "language_acc": {
        "Spanish": 0.9621848739495799,
        "English": 0.9773109243697479,
        "Chinese": 0.373109243697479,
        "Vietnamese": 0.8487394957983193
    },
    "consistency_score_2": 0.634733893557423,
    "consistency_score_3": 0.47016806722689086,
    "consistency_score_4": 0.33613445378151263,
    "detailed_consistency_score": {
        "2_combine": {
            "Spanish,English": 0.9672268907563025,
            "Spanish,Chinese": 0.3773109243697479,
            "Spanish,Vietnamese": 0.8411764705882353,
            "English,Chinese": 0.3773109243697479,
            "English,Vietnamese": 0.846218487394958,
            "Chinese,Vietnamese": 0.39915966386554624
        },
        "3_combine": {
            "Spanish,English,Chinese": 0.36722689075630255,
            "Spanish,English,Vietnamese": 0.83109243697479,
            "Spanish,Chinese,Vietnamese": 0.3411764705882353,
            "English,Chinese,Vietnamese": 0.3411764705882353
        },
        "4_combine": {
            "Spanish,English,Chinese,Vietnamese": 0.33613445378151263
        }
    },
    "AC3_2": 0.7040399726964512,
    "AC3_3": 0.589590756255747,
    "AC3_4": 0.47166647333599176
}